Metadata-Version: 2.4
Name: iflow-mcp_golf-mcp_golf
Version: 0.2.19
Summary: Framework for building MCP servers
Author-email: Antoni Gmitruk <antoni@golf.dev>
License-Expression: Apache-2.0
Project-URL: Homepage, https://golf.dev
Project-URL: Repository, https://github.com/golf-mcp/golf
Classifier: Programming Language :: Python :: 3
Classifier: Operating System :: OS Independent
Classifier: Development Status :: 3 - Alpha
Classifier: Intended Audience :: Developers
Classifier: Topic :: Software Development :: Libraries :: Python Modules
Classifier: Programming Language :: Python :: 3.8
Classifier: Programming Language :: Python :: 3.9
Classifier: Programming Language :: Python :: 3.10
Classifier: Programming Language :: Python :: 3.11
Classifier: Programming Language :: Python :: 3.12
Requires-Python: >=3.8
License-File: LICENSE
Requires-Dist: typer>=0.15.4
Requires-Dist: rich>=14.0.0
Requires-Dist: fastmcp==2.12.5
Requires-Dist: pydantic>=2.11.0
Requires-Dist: pydantic-settings>=2.0.0
Requires-Dist: python-dotenv>=1.1.0
Requires-Dist: black>=24.10.0
Requires-Dist: pyjwt>=2.0.0
Requires-Dist: httpx>=0.28.1
Requires-Dist: posthog>=4.1.0
Requires-Dist: opentelemetry-api>=1.33.1
Requires-Dist: opentelemetry-sdk>=1.33.1
Requires-Dist: opentelemetry-instrumentation-asgi>=0.40b0
Requires-Dist: opentelemetry-exporter-otlp-proto-http>=0.40b0
Requires-Dist: wrapt>=1.17.0
Provides-Extra: metrics
Requires-Dist: prometheus-client>=0.22.1; extra == "metrics"
Dynamic: license-file
